{
  "chapter": 1,
  "title": "The Impossible Data",
  "book": 1,
  "word_count": 2047,
  "date_written": "2025-11-17",
  "temporal_setting": "October 17, 2029 - 2:47 AM",
  "location": "SETI Institute, Mountain View, California",
  "pov_character": "Elliot Cross",
  "key_scenes": [
    "Elliot discovers bootstrap paradox in Voyager 2 signal",
    "Mathematical proof from 2045 verified as accurate",
    "Mysterious warning text arrives",
    "Elliot calls ex-wife Cassandra for help"
  ],
  "characters_present": [
    "Elliot Cross",
    "Cassandra Wright (phone only)"
  ],
  "revelations": [
    "Voyager signal contains future knowledge from 2045",
    "Signal includes unified field theory and device blueprints",
    "Bootstrap paradox is real and operational",
    "Someone is watching Elliot's research"
  ],
  "planted_elements": [
    "Father's determinism philosophy (payoff Ch60)",
    "Cassandra's quantum physics expertise (payoff Ch20, Ch56)",
    "Domino game metaphor (thematic throughline)",
    "Three-layer signal structure (unfolds across trilogy)",
    "Private backup server (becomes important later)"
  ],
  "character_states": {
    "Elliot_Cross": {
      "emotional_state": "Terrified but intellectually excited, exhausted",
      "knowledge": "Confirmed bootstrap paradox, three signal layers, encrypted third layer",
      "relationships": "Reaches out to ex-wife despite two-year separation",
      "arc_position": 0.0
    }
  },
  "themes_explored": [
    "Determinism vs free will introduction",
    "Burden of impossible knowledge",
    "Causality violation as existential threat"
  ],
  "atmosphere": "Noir isolation, rain, 3 AM paranoia, intellectual vertigo",
  "foreshadowing": [
    "Warning text suggests other timelines exist",
    "Encrypted layer 3 contains something crucial",
    "Cassandra's warning that others are looking for signal",
    "Bootstrap loop mechanics established"
  ],
  "temporal_mechanics_established": [
    "Information can travel backward in time",
    "Bootstrap paradox creates closed causal loop",
    "Signal contains multiple layers of increasing importance",
    "Timeline appears predetermined but requires execution"
  ],
  "next_chapter_hooks": [
    "Meeting with Cassandra at 6 AM",
    "Who sent the warning text?",
    "What's in the encrypted third layer?",
    "Who is 'coming for him'?"
  ]
}