{
  "chapter": 4,
  "title": "The Determinism Problem",
  "timestamp": "October 18, 2029 - 2:34 PM",
  "location": "Berkeley, California - Coffee Shop Near Campus",
  "elliot_state": {
    "arc_position": 0.07,
    "temporal_awareness": "Wrestling with free will vs determinism",
    "quantum_coherence": "97% - Minor degradation from processing paradox",
    "philosophical_crisis": "Active - questioning nature of choice",
    "key_realizations": [
      "Free will might be determinism experienced from inside",
      "99.7% probability doesn't eliminate 0.3% genuine uncertainty",
      "Choice matters even within predetermined systems",
      "His father was wrong about free will being meaningless"
    ],
    "emotional_state": "Philosophically destabilized but finding framework"
  },
  "cassandra_state": {
    "arc_position": 0.07,
    "philosophical_position": "Free will exists in quantum uncertainty gaps",
    "support_level": "Actively helping Elliot process existential crisis",
    "relationship_evolution": "Moving from distant ex to philosophical partner"
  },
  "plot_progression": {
    "philosophical_foundation": "Established - determinism and free will as complementary",
    "decision_framework": "Being built - how to make choices in bootstrap loop",
    "recursionist_meeting": "Scheduled for tonight",
    "timeline_pressure": "Building awareness of stakes"
  },
  "themes_developed": {
    "determinism_vs_free_will": "Reframed as perspectives not opposites",
    "burden_of_knowledge": "Knowing future constrains but doesn't eliminate choice",
    "fathers_legacy": "Elliot beginning to transcend father's philosophy"
  },
  "key_quotes": [
    "Free will isn't a switch that's either on or off. It's a spectrum.",
    "Even if you know which domino will fall, someone still has to push it."
  ]
}
