{
  "chapter": 38,
  "title": "The Choice That Matters",
  "word_count": 1900,
  "book": 2,
  "character_states": {
    "Adrian_Keller": {
      "arc_position": 0.64,
      "change_stage": "Stage 3 - last human fragment manifesting and dying",
      "emotional_state": "Residual human caring activating to save Lena, then burning out",
      "crisis": "Demonstrating impossible emotional response - caring when Stage 3 shouldn't allow it",
      "choice": "Stops Lena from transforming despite network benefit",
      "cost": "Last human fragment exhausts itself and dies",
      "knowledge": [
        "Network debated whether to stop Lena",
        "He still had tiny fragment of human caring buried deep",
        "That fragment activated for Lena specifically",
        "Using it burned it out permanently",
        "This was his last human act ever"
      ],
      "transformation_markers": [
        "Last ember of humanity manifesting",
        "One-sided caring without reciprocity",
        "Sacrifice against collective benefit",
        "Fragment dying from the effort"
      ]
    },
    "Network_Collective": {
      "current_size": "921 nodes (not counting Adrian's split awareness)",
      "debate": "Intervention versus autonomy - no consensus",
      "observation": "Witnessing impossible human caring from Stage 3 individual",
      "recognition": "Watching last humanity die, unsure if trade was worth it",
      "philosophical_crisis": "Gained clarity but lost something important"
    },
    "Lena_Martinez": {
      "action": "Infiltrated facility to expose herself to signal",
      "stopped_by": "Adrian preventing her transformation",
      "departure": "Leaves without transforming, saved by his last human act"
    }
  },
  "planted_elements": [
    {
      "element": "Adrian's last human fragment dies after saving Lena",
      "planted_for": "Chapter 39 - aftermath and full posthuman status"
    },
    {
      "element": "Network questioning if they've lost too much",
      "planted_for": "Book 3 - some Changed may seek to maintain humanity"
    },
    {
      "element": "Transformation isn't perfectly uniform - fragments can persist",
      "planted_for": "Hope that something human might remain"
    }
  ],
  "themes_touched": [
    "Last human act as sacrifice",
    "One-sided caring as final gift",
    "Cost of clarity - what's lost in transformation",
    "Network witnessing death of humanity in one of their own"
  ],
  "atmosphere": "Witness to loss, last ember dying, collective uncertainty",
  "key_images": [
    "Adrian's hand stopping Lena's",
    "921 minds watching impossible caring manifest",
    "Network silent as fragment dies",
    "Empty audio lab after Lena leaves",
    "Ember burning out"
  ],
  "foreshadowing": [
    "Complete posthuman transformation imminent for Adrian",
    "Network's growing uncertainty about cost",
    "No human fragments remaining",
    "Voyager's approach in Chapter 40"
  ]
}
