{
  "chapter": 3,
  "title": "The Architecture of Patience",
  "word_count": 2156,
  "timeline": "Day 2,255 of terraforming project (Year 6, Month 2), 5 days after Chapter 2, 8 days after Chapter 1",
  "location": "The Beneath, 3km depth, descending to 4km near mantle",
  "pov_character": "Kessa Okafor",
  "characters_present": ["Kessa Okafor", "Rajesh", "Dr. Chen"],
  "characters_mentioned": ["Dmitri Volkov (via message)"],
  "character_states": {
    "Kessa_Okafor": {
      "knows": [
        "All from Ch1 and Ch2",
        "Structure extends as tunnel networks beneath entire Tharsis region",
        "Tunnels reach down to mantle for geothermal power",
        "Structure actively processes atmospheres (converting Earth-standard back to Mars-standard)",
        "Tunnels connect Olympus, Ascraeus, Pavonis, and Arsia Mons volcanoes",
        "This is planet-wide infrastructure, not isolated structure",
        "Built by indigenous Martian civilization as terraforming maintenance",
        "System still maintaining Mars' atmosphere after 2 million years",
        "Seismic responses correlate with terraforming activity, not excavation",
        "Magnitude 3.5 synchronized quakes across seventeen monitoring stations",
        "Geothermal power station still functional",
        "Corporate review dismissed findings as natural tectonic activity",
        "Excavation permitted to continue with standard protocols"
      ],
      "emotional_state": "Driven by discovery, frustrated by corporate dismissal, growing obsession with understanding before suppression",
      "arc_position": 0.10,
      "location": "Returned to surface, planning next evidence gathering",
      "relationships_affected": {
        "Rajesh": "Loyal but concerned about her pushing too hard",
        "Dr_Chen": "Professional respect, but Chen is frightened by implications",
        "Volkov": "Growing frustration with corporate review process"
      }
    },
    "Rajesh": {
      "knows": [
        "All from Ch2",
        "Chamber actively processes atmospheric compounds",
        "Seismic tremor hit 17 monitoring stations simultaneously",
        "Tunnel networks span continent-sized area",
        "Geothermal power systems still functional",
        "Corporate review dismissed their findings",
        "Kessa is pushing into dangerous territory"
      ],
      "emotional_state": "Excited by discoveries but worried about Kessa and safety",
      "arc_position": 0.06,
      "location": "Olympus Station"
    },
    "Dr_Chen": {
      "knows": [
        "Tunnels descend to mantle depths (structurally impossible by normal geology)",
        "Olympus Mons is dormant volcano, not stable",
        "Magnitude 3.5 quake hit simultaneously across Tharsis region",
        "Structure is planetary-scale atmospheric management system",
        "They are contaminating the system's workspace",
        "This is far more dangerous than standard excavation"
      ],
      "emotional_state": "Frightened by scale and implications, professional concern for safety",
      "arc_position": 0.05,
      "location": "Olympus Station"
    },
    "Dmitri_Volkov": {
      "knows": [
        "All from Ch2",
        "Review committee findings completed",
        "Has seen Kessa's data about planetary-scale networks",
        "Committee determined seismic activity is natural"
      ],
      "emotional_state": "Satisfied that review supports his position, can continue timeline",
      "arc_position": 0.07,
      "location": "Olympus Station corporate sector"
    }
  },
  "revealed_to_reader": [
    "Structure is planet-wide atmospheric management system",
    "Tunnels connect all major Tharsis volcanoes (Olympus, Ascraeus, Pavonis, Arsia Mons)",
    "Tunnels reach to mantle for geothermal power",
    "Chambers actively process atmospheres, converting Earth-standard back to Mars-standard",
    "Structure views human terraforming as contamination to correct",
    "Geothermal power station still functioning after 2 million years",
    "Seismic responses synchronized across seventeen monitoring stations (continental scale)",
    "Magnitude increasing: Ch1: 2.5, Ch2: 3.1, Ch3: 3.5",
    "Corporate review committee dismissed findings as natural tectonic activity",
    "Excavation permitted to continue - no operational changes",
    "System maintains Mars' current atmosphere as endpoint of ancient terraforming",
    "Ancient Martians successfully terraformed Mars, then died out"
  ],
  "planted": [
    {
      "element": "Geothermal power tapping mantle heat",
      "payoff_chapter": 12,
      "significance": "Can trigger volcanic and seismic events across planet"
    },
    {
      "element": "Atmospheric processing chambers converting oxygen back to CO2",
      "payoff_chapter": 12,
      "significance": "The Gardener can reverse terraforming locally"
    },
    {
      "element": "Planet-wide network connecting all Tharsis volcanoes",
      "payoff_chapter": 17,
      "significance": "Can coordinate continent-scale destruction"
    },
    {
      "element": "Corporate review dismissing evidence",
      "payoff_chapter": 7,
      "significance": "Sets up corporate suppression confrontation"
    },
    {
      "element": "System still serving after creators died",
      "payoff_chapter": "Book 2",
      "significance": "Eternal loyalty to dead civilization"
    },
    {
      "element": "Synchronous seismic activity across 17 stations",
      "payoff_chapter": 17,
      "significance": "Proves coordinated planetary response capability"
    },
    {
      "element": "Kessa's obsession with finding undeniable evidence",
      "payoff_chapter": 6,
      "significance": "Drives her to continue despite danger"
    },
    {
      "element": "Chamber 'breathing' metaphor",
      "payoff_chapter": 8,
      "significance": "Structure as living system"
    }
  ],
  "active_tensions": [
    "Kessa vs. corporate dismissal of evidence",
    "Safety concerns vs. need for documentation",
    "Planetary-scale threat vs. terraforming timeline",
    "Team loyalty vs. fear of consequences",
    "Kessa's obsession growing stronger",
    "Magnitude of seismic events escalating"
  ],
  "world_changes": [
    "Full scope of The Gardener revealed to Kessa's team",
    "Corporate review completed and dismissed findings",
    "Excavation permitted to continue",
    "Seismic responses now continent-scale, synchronized",
    "Evidence of active atmospheric management documented"
  ],
  "atmosphere_notes": "Wonder at planetary-scale engineering, growing dread at what it means, frustration with corporate blindness, team fear vs. scientific drive, sense of racing against inevitable suppression",
  "continuity_notes": {
    "timeline": "Day 2,255, 8 days after discovery",
    "seismic_progression": "Ch1: 2.5 localized, Ch2: 3.1 after 72 hrs, Ch3: 3.5 synchronized across 17 stations",
    "structure_scale": "Planet-wide network, connects Olympus/Ascraeus/Pavonis/Arsia Mons, reaches to mantle",
    "character_voices": "Kessa: academic excitement overriding caution; Chen: frightened geologist; Rajesh: loyal but worried",
    "technology": "Ground-penetrating radar, handheld scanners, helmet comms and displays, atmospheric analysis",
    "mars_details": "Olympus Mons = largest volcano in solar system (dormant), Tharsis region = continent-sized area",
    "atmospheric_chamber": "Converting Earth-standard (O2/N2) back to Mars-standard (CO2/trace)",
    "bioluminescence": "Crystalline structures pulse with light, rhythm changes with system activity"
  }
}
