{
  "chapter": 1,
  "title": "The Authentication Error",
  "word_count": 2089,
  "timeline": "Day 1, Tuesday morning, pre-dawn to sunrise",
  "location": "The Vault - Archive room, Level 93, Neo-Singapore",
  "characters_present": ["Aria Chen"],
  "pov_character": "Aria Chen",
  "character_states": {
    "aria_chen": {
      "location": "The Vault, archive room",
      "emotional_state": "Professional certainty → creeping doubt → existential dread → determined resolve",
      "arc_position": 0.05,
      "knows": [
        "She has 17 modified memories",
        "Modifications occurred 2 years ago",
        "All backups older than 2 years are corrupted",
        "Memory editing happened in this vault using corporate equipment",
        "Her employment records claim 8 years, but reliable memories only go back 2 years",
        "Emergency maintenance session on her consciousness 2 years ago at 3:47 AM, duration 4 hours 17 minutes",
        "Session had executive override authorization but no supervising technician on record",
        "She can't access memories before 2 years ago clearly - they're static/fractured"
      ],
      "does_not_know": [
        "She is a Composite (discovers in ch12)",
        "Who edited her memories or why",
        "What her memories were before editing",
        "Who authorized the executive override",
        "The Archivist's existence or involvement",
        "Marcus Webb exists",
        "Government conspiracy scope",
        "Her true age (2 years, not 8+ years)"
      ],
      "decisions_made": [
        "Concealed discovery from supervisor - lied about self-audit results",
        "Deleted evidence of forensic scan from system logs",
        "Decided to investigate independently rather than report through official channels",
        "Sent encrypted log to dead-drop server for backup"
      ],
      "skills_demonstrated": [
        "Memory authentication expertise",
        "Forensic analysis of quantum signatures",
        "System access and log investigation",
        "Data encryption and concealment"
      ]
    }
  },
  "revealed_to_reader": [
    "Memory authentication technology using quantum signatures",
    "Neural implants are standard for citizens",
    "Consciousness backup every 6 months is normal corporate policy",
    "Memory can be bought, sold, and illegally manipulated",
    "Memory theft is punishable by 'consciousness dissolution' (death)",
    "Society divided into Originals, Augmented, Composites, Blanks (not fully explained yet)",
    "Neo-Singapore megacity setting with Undercity memory markets",
    "The Vault facility spans at least 93 floors",
    "0.3% degradation rate per memory transfer (implied by baseline variance)",
    "Quantum signature manipulation leaves detectable traces that fade after 72 hours (implied)",
    "Aria's memories have been systematically edited"
  ],
  "planted": [
    {
      "element": "17 modified memories from 2 years ago",
      "payoff_chapter": 12,
      "significance": "Marks when Aria was created as Composite, original memories replaced"
    },
    {
      "element": "Corrupted backups older than 2 years",
      "payoff_chapter": 12,
      "significance": "No backups exist because Aria didn't exist before then"
    },
    {
      "element": "4 hour 17 minute consciousness session with executive override",
      "payoff_chapter": 17,
      "significance": "When she was programmed with her mission to infiltrate vault"
    },
    {
      "element": "Fractured childhood memories - presence of nothing",
      "payoff_chapter": 12,
      "significance": "Composite construction - memories don't exist because childhood didn't happen"
    },
    {
      "element": "Scanner's three-tone sequence (A-flat, C, E)",
      "payoff_chapter": null,
      "significance": "Recurring motif throughout book - the question being asked repeatedly"
    },
    {
      "element": "Authentication as religion for Aria",
      "payoff_chapter": 17,
      "significance": "Her choice to expose conspiracy even though it reveals her own inauthenticity"
    },
    {
      "element": "Dead-drop server for emergency backup",
      "payoff_chapter": 7,
      "significance": "Where she'll send evidence to Marcus, or where Marcus finds evidence"
    },
    {
      "element": "Undercity memory markets mentioned",
      "payoff_chapter": 7,
      "significance": "Where she'll meet Marcus or investigate further"
    },
    {
      "element": "Equipment in this vault was used for manipulation",
      "payoff_chapter": 17,
      "significance": "The Vault is compromised at highest levels, corporate conspiracy"
    }
  ],
  "active_tensions": [
    "Aria's professional duty vs. need to investigate her own compromised memories",
    "Who edited her memories and why",
    "Whether she can trust any of her own memories or identity",
    "Risk of discovery if she investigates further",
    "What happened 2 years ago that required her consciousness to be edited"
  ],
  "world_rules_established": {
    "memory_transfer_technology": [
      "Quantum signature authentication is standard verification method",
      "Neural implants are common, visible at temple",
      "Consciousness backup every 6 months is corporate policy",
      "Memory editing requires direct neural implant access and sophisticated equipment",
      "Quantum signatures can be forged but leave detectable traces",
      "High-precision quantum entanglement reassignment is cutting-edge manipulation method"
    ],
    "social_structures": [
      "Memory theft punished by consciousness dissolution",
      "Legal memory markets exist (skill memories, emotional experiences)",
      "Black market operates in Undercity with illegal memory trade",
      "Corporate employment includes mandatory self-audits",
      "Vault facilities store high-value consciousness backups"
    ],
    "setting": [
      "Neo-Singapore megacity, 2187",
      "Dense urban environment with Undercity districts",
      "Neon-lit aesthetic, pre-dawn pink and electric blue",
      "Corporate towers of 90+ floors",
      "Memory market vendors operate legally and illegally"
    ]
  },
  "atmosphere": {
    "tone": "Noir thriller with existential dread",
    "mood": "Paranoid, precise, isolated, building suspense",
    "sensory_details": [
      "Scanner's three-tone hum: A-flat, C, E",
      "Coffee cooling, then spilling and spreading",
      "Sterile environmental systems breathing",
      "Neon glow through reinforced windows - pink and blue",
      "Empty archive room, very quiet",
      "Holographic displays in blue light"
    ],
    "visual_motifs": [
      "Consciousness rendered as crystalline lattice",
      "Coffee spill like ink writing message",
      "Reflection in window - questioning who looks back",
      "Sunrise turning neon darkness into day"
    ]
  },
  "style_notes": {
    "aria_voice_markers_used": [
      "Precise, technical language when discussing memory systems",
      "Speaking protocol steps aloud: 'Say it, check it, verify it'",
      "Professional certainty in early sections",
      "Becomes more fragmented and questioning as discovery unfolds",
      "Memory-related metaphors: 'static', 'smoke', 'fractured'"
    ],
    "sentence_rhythm": "Varied - short declarative sentences for technical precision, longer flowing sentences for emotional moments, fragment sentences for shock/realization",
    "pacing": "Slow build → discovery → acceleration → determination"
  },
  "continuity_notes": {
    "timeline": "This is the beginning of the trilogy timeline, Day 1",
    "character_knowledge": "Aria knows something is wrong but has no context for conspiracy scope",
    "world_state": "Society still functioning normally, conspiracy not yet exposed",
    "relationship_establishment": "Aria is isolated, no relationships shown yet"
  },
  "foreshadowing": [
    "Question of who Aria really is (she's a Composite)",
    "Her dedication to authenticity will be tested when she learns she's not authentic",
    "The vault she protects is the source of conspiracy",
    "Executive override authorization hints at high-level conspiracy",
    "Her instinct to investigate rather than report shows independence that will matter later"
  ],
  "chapter_function": {
    "plot": "Inciting incident - Aria discovers her memories are compromised",
    "character": "Establishes Aria's expertise, dedication, and capacity for independent action",
    "world": "Introduces memory technology, vault setting, social structure basics",
    "theme": "Identity beyond memory - what if your memories aren't yours?",
    "reader_engagement": "Mystery hook - who is Aria really? What was done to her?"
  }
}
